{"id":"52mjeqlcvu5841t72251ea5","title":"Stand Up","desc":"","updated":1656420436917,"created":1656079582899,"custom":{},"fname":"dpd.pcg-b.2022.06.27.stand-up","type":"note","vault":{"fsPath":"meetings"},"contentHash":"6537c4ca40c5a22893e3187ccb7b0e55","links":[{"type":"wiki","from":{"fname":"dpd.pcg-b.2022.06.27.stand-up","id":"52mjeqlcvu5841t72251ea5","vaultName":"meetings"},"value":"dpd.pcg-b.2022.06.24.stand-up","alias":"June 24 Stand Up","position":{"start":{"line":4,"column":1,"offset":15},"end":{"line":4,"column":51,"offset":65},"indent":[]},"xvault":false,"sameFile":false,"to":{"fname":"dpd.pcg-b.2022.06.24.stand-up"}},{"type":"wiki","from":{"fname":"dpd.pcg-b.2022.06.27.stand-up","id":"52mjeqlcvu5841t72251ea5","vaultName":"meetings"},"value":"user.stories.POW-145","alias":"@stories.POW-145","position":{"start":{"line":9,"column":3,"offset":822},"end":{"line":9,"column":19,"offset":838},"indent":[]},"xvault":false,"to":{"fname":"user.stories.POW-145"}},{"type":"wiki","from":{"fname":"dpd.pcg-b.2022.06.27.stand-up","id":"52mjeqlcvu5841t72251ea5","vaultName":"meetings"},"value":"user.people.SoumyajitPaul","alias":"@people.SoumyajitPaul","position":{"start":{"line":9,"column":72,"offset":891},"end":{"line":9,"column":93,"offset":912},"indent":[]},"xvault":false,"to":{"fname":"user.people.SoumyajitPaul"}},{"type":"wiki","from":{"fname":"dpd.pcg-b.2022.06.27.stand-up","id":"52mjeqlcvu5841t72251ea5","vaultName":"meetings"},"value":"user.stories.PCGQC-9","alias":"@stories.PCGQC-9","position":{"start":{"line":10,"column":3,"offset":1072},"end":{"line":10,"column":19,"offset":1088},"indent":[]},"xvault":false,"to":{"fname":"user.stories.PCGQC-9"}},{"type":"wiki","from":{"fname":"dpd.pcg-b.2022.06.27.stand-up","id":"52mjeqlcvu5841t72251ea5","vaultName":"meetings"},"value":"user.stories.POW-152","alias":"@stories.POW-152","position":{"start":{"line":13,"column":3,"offset":1825},"end":{"line":13,"column":19,"offset":1841},"indent":[]},"xvault":false,"to":{"fname":"user.stories.POW-152"}},{"type":"wiki","from":{"fname":"dpd.pcg-b.2022.06.27.stand-up","id":"52mjeqlcvu5841t72251ea5","vaultName":"meetings"},"value":"user.people.GunabalanAnatharajan","alias":"@people.GunabalanAnatharajan","position":{"start":{"line":13,"column":72,"offset":1894},"end":{"line":13,"column":100,"offset":1922},"indent":[]},"xvault":false,"to":{"fname":"user.people.GunabalanAnatharajan"}},{"type":"wiki","from":{"fname":"dpd.pcg-b.2022.06.27.stand-up","id":"52mjeqlcvu5841t72251ea5","vaultName":"meetings"},"value":"user.stories.POW-199","alias":"@stories.POW-199","position":{"start":{"line":14,"column":3,"offset":2076},"end":{"line":14,"column":19,"offset":2092},"indent":[]},"xvault":false,"to":{"fname":"user.stories.POW-199"}},{"type":"wiki","from":{"fname":"dpd.pcg-b.2022.06.27.stand-up","id":"52mjeqlcvu5841t72251ea5","vaultName":"meetings"},"value":"user.people.HieuNgo","alias":"@people.HieuNgo","position":{"start":{"line":14,"column":72,"offset":2145},"end":{"line":14,"column":87,"offset":2160},"indent":[]},"xvault":false,"to":{"fname":"user.people.HieuNgo"}},{"type":"wiki","from":{"fname":"dpd.pcg-b.2022.06.27.stand-up","id":"52mjeqlcvu5841t72251ea5","vaultName":"meetings"},"value":"user.stories.POW-215","alias":"@stories.POW-215","position":{"start":{"line":15,"column":3,"offset":2327},"end":{"line":15,"column":19,"offset":2343},"indent":[]},"xvault":false,"to":{"fname":"user.stories.POW-215"}},{"type":"wiki","from":{"fname":"dpd.pcg-b.2022.06.27.stand-up","id":"52mjeqlcvu5841t72251ea5","vaultName":"meetings"},"value":"user.people.EarlSioson","alias":"@people.EarlSioson","position":{"start":{"line":15,"column":72,"offset":2396},"end":{"line":15,"column":90,"offset":2414},"indent":[]},"xvault":false,"to":{"fname":"user.people.EarlSioson"}},{"type":"wiki","from":{"fname":"dpd.pcg-b.2022.06.27.stand-up","id":"52mjeqlcvu5841t72251ea5","vaultName":"meetings"},"value":"user.stories.POW-177","alias":"@stories.POW-177","position":{"start":{"line":16,"column":3,"offset":2578},"end":{"line":16,"column":19,"offset":2594},"indent":[]},"xvault":false,"to":{"fname":"user.stories.POW-177"}},{"type":"wiki","from":{"fname":"dpd.pcg-b.2022.06.27.stand-up","id":"52mjeqlcvu5841t72251ea5","vaultName":"meetings"},"value":"user.people.HieuNgo","alias":"@people.HieuNgo","position":{"start":{"line":16,"column":72,"offset":2647},"end":{"line":16,"column":87,"offset":2662},"indent":[]},"xvault":false,"to":{"fname":"user.people.HieuNgo"}},{"type":"wiki","from":{"fname":"dpd.pcg-b.2022.06.27.stand-up","id":"52mjeqlcvu5841t72251ea5","vaultName":"meetings"},"value":"user.stories.POW-222","alias":"@stories.POW-222","position":{"start":{"line":17,"column":3,"offset":2829},"end":{"line":17,"column":19,"offset":2845},"indent":[]},"xvault":false,"to":{"fname":"user.stories.POW-222"}},{"type":"wiki","from":{"fname":"dpd.pcg-b.2022.06.27.stand-up","id":"52mjeqlcvu5841t72251ea5","vaultName":"meetings"},"value":"user.people.JustinDruga","alias":"@people.JustinDruga","position":{"start":{"line":17,"column":72,"offset":2898},"end":{"line":17,"column":91,"offset":2917},"indent":[]},"xvault":false,"to":{"fname":"user.people.JustinDruga"}},{"type":"wiki","from":{"fname":"dpd.pcg-b.2022.06.27.stand-up","id":"52mjeqlcvu5841t72251ea5","vaultName":"meetings"},"value":"user.stories.PCGQC-2","alias":"@stories.PCGQC-2","position":{"start":{"line":18,"column":3,"offset":3080},"end":{"line":18,"column":19,"offset":3096},"indent":[]},"xvault":false,"to":{"fname":"user.stories.PCGQC-2"}},{"type":"wiki","from":{"fname":"dpd.pcg-b.2022.06.27.stand-up","id":"52mjeqlcvu5841t72251ea5","vaultName":"meetings"},"value":"user.stories.PCGQC-34","alias":"@stories.PCGQC-34","position":{"start":{"line":19,"column":3,"offset":3331},"end":{"line":19,"column":20,"offset":3348},"indent":[]},"xvault":false,"to":{"fname":"user.stories.PCGQC-34"}},{"type":"wiki","from":{"fname":"dpd.pcg-b.2022.06.27.stand-up","id":"52mjeqlcvu5841t72251ea5","vaultName":"meetings"},"value":"user.stories.PCGQC-3","alias":"@stories.PCGQC-3","position":{"start":{"line":20,"column":3,"offset":3582},"end":{"line":20,"column":19,"offset":3598},"indent":[]},"xvault":false,"to":{"fname":"user.stories.PCGQC-3"}},{"type":"wiki","from":{"fname":"dpd.pcg-b.2022.06.27.stand-up","id":"52mjeqlcvu5841t72251ea5","vaultName":"meetings"},"value":"user.stories.PCGQC-1","alias":"@stories.PCGQC-1","position":{"start":{"line":21,"column":3,"offset":3833},"end":{"line":21,"column":19,"offset":3849},"indent":[]},"xvault":false,"to":{"fname":"user.stories.PCGQC-1"}},{"type":"wiki","from":{"fname":"dpd.pcg-b.2022.06.27.stand-up","id":"52mjeqlcvu5841t72251ea5","vaultName":"meetings"},"value":"user.stories.PCGQC-131","alias":"@stories.PCGQC-131","position":{"start":{"line":22,"column":3,"offset":4084},"end":{"line":22,"column":21,"offset":4102},"indent":[]},"xvault":false,"to":{"fname":"user.stories.PCGQC-131"}},{"type":"wiki","from":{"fname":"dpd.pcg-b.2022.06.27.stand-up","id":"52mjeqlcvu5841t72251ea5","vaultName":"meetings"},"value":"user.people.RahulLange","alias":"@people.RahulLange","position":{"start":{"line":22,"column":72,"offset":4153},"end":{"line":22,"column":90,"offset":4171},"indent":[]},"xvault":false,"to":{"fname":"user.people.RahulLange"}},{"type":"wiki","from":{"fname":"dpd.pcg-b.2022.06.27.stand-up","id":"52mjeqlcvu5841t72251ea5","vaultName":"meetings"},"value":"user.stories.PCGQC-135","alias":"@stories.PCGQC-135","position":{"start":{"line":23,"column":3,"offset":4335},"end":{"line":23,"column":21,"offset":4353},"indent":[]},"xvault":false,"to":{"fname":"user.stories.PCGQC-135"}},{"type":"wiki","from":{"fname":"dpd.pcg-b.2022.06.27.stand-up","id":"52mjeqlcvu5841t72251ea5","vaultName":"meetings"},"value":"user.people.ChirayuPoundarik","alias":"@people.ChirayuPoundarik","position":{"start":{"line":23,"column":72,"offset":4404},"end":{"line":23,"column":96,"offset":4428},"indent":[]},"xvault":false,"to":{"fname":"user.people.ChirayuPoundarik"}},{"type":"wiki","from":{"fname":"dpd.pcg-b.2022.06.27.stand-up","id":"52mjeqlcvu5841t72251ea5","vaultName":"meetings"},"value":"user.stories.POW-202","alias":"@stories.POW-202","position":{"start":{"line":26,"column":3,"offset":5088},"end":{"line":26,"column":19,"offset":5104},"indent":[]},"xvault":false,"to":{"fname":"user.stories.POW-202"}},{"type":"wiki","from":{"fname":"dpd.pcg-b.2022.06.27.stand-up","id":"52mjeqlcvu5841t72251ea5","vaultName":"meetings"},"value":"user.people.SoumyajitPaul","alias":"@people.SoumyajitPaul","position":{"start":{"line":26,"column":72,"offset":5157},"end":{"line":26,"column":93,"offset":5178},"indent":[]},"xvault":false,"to":{"fname":"user.people.SoumyajitPaul"}},{"type":"wiki","from":{"fname":"dpd.pcg-b.2022.06.27.stand-up","id":"52mjeqlcvu5841t72251ea5","vaultName":"meetings"},"value":"user.stories.POW-130","alias":"@stories.POW-130","position":{"start":{"line":27,"column":3,"offset":5338},"end":{"line":27,"column":19,"offset":5354},"indent":[]},"xvault":false,"to":{"fname":"user.stories.POW-130"}},{"type":"wiki","from":{"fname":"dpd.pcg-b.2022.06.27.stand-up","id":"52mjeqlcvu5841t72251ea5","vaultName":"meetings"},"value":"user.people.BrianComiskey","alias":"@people.BrianComiskey","position":{"start":{"line":27,"column":72,"offset":5407},"end":{"line":27,"column":93,"offset":5428},"indent":[]},"xvault":false,"to":{"fname":"user.people.BrianComiskey"}},{"type":"wiki","from":{"fname":"dpd.pcg-b.2022.06.27.stand-up","id":"52mjeqlcvu5841t72251ea5","vaultName":"meetings"},"value":"user.stories.POW-139","alias":"@stories.POW-139","position":{"start":{"line":31,"column":3,"offset":6342},"end":{"line":31,"column":19,"offset":6358},"indent":[]},"xvault":false,"to":{"fname":"user.stories.POW-139"}},{"type":"wiki","from":{"fname":"dpd.pcg-b.2022.06.27.stand-up","id":"52mjeqlcvu5841t72251ea5","vaultName":"meetings"},"value":"user.people.GunabalanAnatharajan","alias":"@people.GunabalanAnatharajan","position":{"start":{"line":31,"column":72,"offset":6411},"end":{"line":31,"column":100,"offset":6439},"indent":[]},"xvault":false,"to":{"fname":"user.people.GunabalanAnatharajan"}},{"type":"wiki","from":{"fname":"dpd.pcg-b.2022.06.27.stand-up","id":"52mjeqlcvu5841t72251ea5","vaultName":"meetings"},"value":"user.stories.POW-146","alias":"@stories.POW-146","position":{"start":{"line":32,"column":3,"offset":6593},"end":{"line":32,"column":19,"offset":6609},"indent":[]},"xvault":false,"to":{"fname":"user.stories.POW-146"}},{"type":"wiki","from":{"fname":"dpd.pcg-b.2022.06.27.stand-up","id":"52mjeqlcvu5841t72251ea5","vaultName":"meetings"},"value":"user.people.GunabalanAnatharajan","alias":"@people.GunabalanAnatharajan","position":{"start":{"line":32,"column":72,"offset":6662},"end":{"line":32,"column":100,"offset":6690},"indent":[]},"xvault":false,"to":{"fname":"user.people.GunabalanAnatharajan"}},{"type":"wiki","from":{"fname":"dpd.pcg-b.2022.06.27.stand-up","id":"52mjeqlcvu5841t72251ea5","vaultName":"meetings"},"value":"user.stories.POW-181","alias":"@stories.POW-181","position":{"start":{"line":33,"column":3,"offset":6844},"end":{"line":33,"column":19,"offset":6860},"indent":[]},"xvault":false,"to":{"fname":"user.stories.POW-181"}},{"type":"wiki","from":{"fname":"dpd.pcg-b.2022.06.27.stand-up","id":"52mjeqlcvu5841t72251ea5","vaultName":"meetings"},"value":"user.people.EarlSioson","alias":"@people.EarlSioson","position":{"start":{"line":33,"column":72,"offset":6913},"end":{"line":33,"column":90,"offset":6931},"indent":[]},"xvault":false,"to":{"fname":"user.people.EarlSioson"}},{"from":{"fname":"dpd.pcg-b.2022.06.28.stand-up","vaultName":"meetings"},"type":"backlink","position":{"start":{"line":4,"column":1,"offset":15},"end":{"line":4,"column":51,"offset":65},"indent":[]},"value":"dpd.pcg-b.2022.06.27.stand-up","alias":"June 27 Stand Up"}],"anchors":{"previous":{"type":"header","text":"Previous","value":"previous","line":8,"column":0,"depth":3}},"children":[],"parent":"23i54aao9bm0f83k6oou61b","data":{}}
