{"id":"ls4f3qbg2zr4ouhrl2f7vlz","title":"Collaboration and Self Management in Agile Environments","desc":"","updated":1654018676266,"created":1654018641239,"custom":{},"fname":"training.pluralsight.scrum.collaboration-and-self-management-in-agile-environments","type":"note","vault":{"fsPath":"meetings"},"contentHash":"0fc8337d786f06edab0a571d0a24553b","links":[{"type":"wiki","from":{"fname":"training.pluralsight.scrum.collaboration-and-self-management-in-agile-environments","id":"ls4f3qbg2zr4ouhrl2f7vlz","vaultName":"meetings"},"value":"training.pluralsight.scrum.agile-transformation","alias":"Collaboration & Self Management in Agile Environments","position":{"start":{"line":2,"column":1,"offset":1},"end":{"line":2,"column":159,"offset":159},"indent":[]},"xvault":false,"sameFile":false,"to":{"fname":"training.pluralsight.scrum.agile-transformation","anchorHeader":"collaboration--self-management-in-agile-environments"}}],"anchors":{},"children":[],"parent":"o53wni7z258rzxtzfsshz4e","data":{}}
